[
    {
      "_id": 101,
      "name": "Chicken Udon Soup",
      "price": 11.99,
      "ingredients": ["chicken stock", "udon", "chicken breast"]
    },
    {
      "_id": 203,
      "name": "Salmon Teriyaki Don",
      "price": 9.9,
      "ingredients": ["salmon", "rice", "soya sauce"]
    },
    {
      "_id": 401,
      "name": "Raw Salmon Slices",
      "price": 15.99,
      "ingredients": ["salmon"]
    },
    {
      "_id": 402,
      "name": "Chicken Miso Ramen",
      "price": 15.99,
      "ingredients": ["chicken", "miso", "ramen"]
    }
  ]
  